{
  "content": [
    {
      "content": null,
      "created": "2025-09-23T08:41:10.486591Z",
      "format": null,
      "hash": null,
      "hash_algorithm": null,
      "last_modified": "2025-09-23T08:41:10.486591Z",
      "mimetype": null,
      "name": "mathematical_optimization",
      "path": "advanced/mathematical_optimization",
      "size": null,
      "type": "directory",
      "writable": true
    },
    {
      "content": null,
      "created": "2025-09-23T08:41:10.483347Z",
      "format": null,
      "hash": null,
      "hash_algorithm": null,
      "last_modified": "2025-09-23T08:41:10.483347Z",
      "mimetype": null,
      "name": "advanced_numpy",
      "path": "advanced/advanced_numpy",
      "size": null,
      "type": "directory",
      "writable": true
    },
    {
      "content": null,
      "created": "2025-09-23T08:41:10.484117Z",
      "format": null,
      "hash": null,
      "hash_algorithm": null,
      "last_modified": "2025-09-23T08:41:10.484117Z",
      "mimetype": null,
      "name": "advanced_python",
      "path": "advanced/advanced_python",
      "size": null,
      "type": "directory",
      "writable": true
    },
    {
      "content": null,
      "created": "2025-09-23T08:41:10.484793Z",
      "format": null,
      "hash": null,
      "hash_algorithm": null,
      "last_modified": "2025-09-23T08:41:10.484793Z",
      "mimetype": null,
      "name": "debugging",
      "path": "advanced/debugging",
      "size": null,
      "type": "directory",
      "writable": true
    },
    {
      "content": null,
      "created": "2025-09-23T08:41:10.491397Z",
      "format": null,
      "hash": null,
      "hash_algorithm": null,
      "last_modified": "2025-09-23T08:41:10.491397Z",
      "mimetype": null,
      "name": "scipy_sparse",
      "path": "advanced/scipy_sparse",
      "size": null,
      "type": "directory",
      "writable": true
    },
    {
      "content": null,
      "created": "2025-09-23T08:41:10.485984Z",
      "format": null,
      "hash": null,
      "hash_algorithm": null,
      "last_modified": "2025-09-23T08:41:10.485984Z",
      "mimetype": null,
      "name": "interfacing_with_c",
      "path": "advanced/interfacing_with_c",
      "size": null,
      "type": "directory",
      "writable": true
    },
    {
      "content": null,
      "created": "2025-09-23T08:41:10.487310Z",
      "format": null,
      "hash": null,
      "hash_algorithm": null,
      "last_modified": "2025-09-23T08:41:10.487310Z",
      "mimetype": null,
      "name": "optimizing",
      "path": "advanced/optimizing",
      "size": null,
      "type": "directory",
      "writable": true
    },
    {
      "content": null,
      "created": "2025-09-23T08:41:10.485356Z",
      "format": null,
      "hash": null,
      "hash_algorithm": null,
      "last_modified": "2025-09-23T08:41:10.485356Z",
      "mimetype": null,
      "name": "image_processing",
      "path": "advanced/image_processing",
      "size": null,
      "type": "directory",
      "writable": true
    }
  ],
  "created": "2025-09-23T08:41:10.487700Z",
  "format": "json",
  "hash": null,
  "hash_algorithm": null,
  "last_modified": "2025-09-23T08:41:10.487700Z",
  "mimetype": null,
  "name": "advanced",
  "path": "advanced",
  "size": null,
  "type": "directory",
  "writable": true
}