{
  "content": [
    {
      "content": null,
      "created": "2025-09-25T11:36:00.240422Z",
      "format": null,
      "hash": null,
      "hash_algorithm": null,
      "last_modified": "2025-09-25T11:35:48.239540Z",
      "mimetype": null,
      "name": "index.ipynb",
      "path": "advanced/advanced_numpy/index.ipynb",
      "size": 64592,
      "type": "notebook",
      "writable": true
    }
  ],
  "created": "2025-09-25T11:36:00.239983Z",
  "format": "json",
  "hash": null,
  "hash_algorithm": null,
  "last_modified": "2025-09-25T11:36:00.239983Z",
  "mimetype": null,
  "name": "advanced_numpy",
  "path": "advanced/advanced_numpy",
  "size": null,
  "type": "directory",
  "writable": true
}