{
  "content": [
    {
      "content": null,
      "created": "2025-09-30T16:47:03.040515Z",
      "format": null,
      "hash": null,
      "hash_algorithm": null,
      "last_modified": "2025-09-30T16:46:56.070262Z",
      "mimetype": null,
      "name": "index.ipynb",
      "path": "advanced/image_processing/index.ipynb",
      "size": 44365,
      "type": "notebook",
      "writable": true
    }
  ],
  "created": "2025-09-30T16:47:03.040173Z",
  "format": "json",
  "hash": null,
  "hash_algorithm": null,
  "last_modified": "2025-09-30T16:47:03.040173Z",
  "mimetype": null,
  "name": "image_processing",
  "path": "advanced/image_processing",
  "size": null,
  "type": "directory",
  "writable": true
}