{
  "content": [
    {
      "content": null,
      "created": "2025-09-25T08:52:24.109622Z",
      "format": null,
      "hash": null,
      "hash_algorithm": null,
      "last_modified": "2025-09-25T08:52:14.748235Z",
      "mimetype": null,
      "name": "help.ipynb",
      "path": "intro/help/help.ipynb",
      "size": 4357,
      "type": "notebook",
      "writable": true
    }
  ],
  "created": "2025-09-25T08:52:24.109298Z",
  "format": "json",
  "hash": null,
  "hash_algorithm": null,
  "last_modified": "2025-09-25T08:52:24.109298Z",
  "mimetype": null,
  "name": "help",
  "path": "intro/help",
  "size": null,
  "type": "directory",
  "writable": true
}