{
  "content": [
    {
      "content": null,
      "created": "2025-09-30T12:06:07.009665Z",
      "format": null,
      "hash": null,
      "hash_algorithm": null,
      "last_modified": "2025-09-30T12:06:03.075984Z",
      "mimetype": null,
      "name": "intro.ipynb",
      "path": "intro/intro.ipynb",
      "size": 17959,
      "type": "notebook",
      "writable": true
    },
    {
      "content": null,
      "created": "2025-09-30T12:06:07.013779Z",
      "format": null,
      "hash": null,
      "hash_algorithm": null,
      "last_modified": "2025-09-30T12:06:07.013779Z",
      "mimetype": null,
      "name": "language",
      "path": "intro/language",
      "size": null,
      "type": "directory",
      "writable": true
    },
    {
      "content": null,
      "created": "2025-09-30T12:06:07.017661Z",
      "format": null,
      "hash": null,
      "hash_algorithm": null,
      "last_modified": "2025-09-30T12:06:07.017661Z",
      "mimetype": null,
      "name": "numpy",
      "path": "intro/numpy",
      "size": null,
      "type": "directory",
      "writable": true
    },
    {
      "content": null,
      "created": "2025-09-30T12:06:07.014921Z",
      "format": null,
      "hash": null,
      "hash_algorithm": null,
      "last_modified": "2025-09-30T12:06:07.014921Z",
      "mimetype": null,
      "name": "matplotlib",
      "path": "intro/matplotlib",
      "size": null,
      "type": "directory",
      "writable": true
    },
    {
      "content": null,
      "created": "2025-09-30T12:06:07.019690Z",
      "format": null,
      "hash": null,
      "hash_algorithm": null,
      "last_modified": "2025-09-30T12:06:07.019690Z",
      "mimetype": null,
      "name": "scipy",
      "path": "intro/scipy",
      "size": null,
      "type": "directory",
      "writable": true
    },
    {
      "content": null,
      "created": "2025-09-30T12:06:07.009274Z",
      "format": null,
      "hash": null,
      "hash_algorithm": null,
      "last_modified": "2025-09-30T12:06:03.063091Z",
      "mimetype": null,
      "name": "index.ipynb",
      "path": "intro/index.ipynb",
      "size": 527,
      "type": "notebook",
      "writable": true
    },
    {
      "content": null,
      "created": "2025-09-30T12:06:07.008476Z",
      "format": null,
      "hash": null,
      "hash_algorithm": null,
      "last_modified": "2025-09-30T12:06:07.008476Z",
      "mimetype": null,
      "name": "help",
      "path": "intro/help",
      "size": null,
      "type": "directory",
      "writable": true
    }
  ],
  "created": "2025-09-30T12:06:07.018113Z",
  "format": "json",
  "hash": null,
  "hash_algorithm": null,
  "last_modified": "2025-09-30T12:06:07.018113Z",
  "mimetype": null,
  "name": "intro",
  "path": "intro",
  "size": null,
  "type": "directory",
  "writable": true
}