{
  "content": [
    {
      "content": null,
      "created": "2025-09-23T22:50:49.762445Z",
      "format": null,
      "hash": null,
      "hash_algorithm": null,
      "last_modified": "2025-09-23T22:50:42.667105Z",
      "mimetype": null,
      "name": "exercises.ipynb",
      "path": "intro/numpy/exercises.ipynb",
      "size": 12395,
      "type": "notebook",
      "writable": true
    },
    {
      "content": null,
      "created": "2025-09-23T22:50:49.761686Z",
      "format": null,
      "hash": null,
      "hash_algorithm": null,
      "last_modified": "2025-09-23T22:50:42.598583Z",
      "mimetype": null,
      "name": "elaborate_arrays.ipynb",
      "path": "intro/numpy/elaborate_arrays.ipynb",
      "size": 11941,
      "type": "notebook",
      "writable": true
    },
    {
      "content": null,
      "created": "2025-09-23T22:50:49.773055Z",
      "format": null,
      "hash": null,
      "hash_algorithm": null,
      "last_modified": "2025-09-23T22:50:42.905620Z",
      "mimetype": null,
      "name": "operations.ipynb",
      "path": "intro/numpy/operations.ipynb",
      "size": 36196,
      "type": "notebook",
      "writable": true
    },
    {
      "content": null,
      "created": "2025-09-23T22:50:49.760823Z",
      "format": null,
      "hash": null,
      "hash_algorithm": null,
      "last_modified": "2025-09-23T22:50:42.508131Z",
      "mimetype": null,
      "name": "array_object.ipynb",
      "path": "intro/numpy/array_object.ipynb",
      "size": 32902,
      "type": "notebook",
      "writable": true
    },
    {
      "content": null,
      "created": "2025-09-23T22:50:49.760050Z",
      "format": null,
      "hash": null,
      "hash_algorithm": null,
      "last_modified": "2025-09-23T22:50:42.337135Z",
      "mimetype": null,
      "name": "advanced_operations.ipynb",
      "path": "intro/numpy/advanced_operations.ipynb",
      "size": 9736,
      "type": "notebook",
      "writable": true
    }
  ],
  "created": "2025-09-23T22:50:49.772674Z",
  "format": "json",
  "hash": null,
  "hash_algorithm": null,
  "last_modified": "2025-09-23T22:50:49.772674Z",
  "mimetype": null,
  "name": "numpy",
  "path": "intro/numpy",
  "size": null,
  "type": "directory",
  "writable": true
}